manjaro_torrent_find/__init__.py
manjaro_torrent_find/mtf.py
manjaro_torrent_find-0.3.1.dist-info/entry_points.txt
manjaro_torrent_find-0.3.1.dist-info/LICENSE
manjaro_torrent_find-0.3.1.dist-info/WHEEL
manjaro_torrent_find-0.3.1.dist-info/METADATA
manjaro_torrent_find-0.3.1.dist-info/RECORD
