Metadata-Version: 2.1
Name: manjaro-torrent-find
Version: 0.3.1
Summary: Searches the OSDN Manjaro project for torrent files and downloads them.
Home-page: https://github.com/ccdale/manjaro-torrent-find
License: GPL-3.0-or-later
Author: Chris Allison
Author-email: chris.charles.allison+mtf@gmail.com
Requires-Python: >=3.6,<4.0
Classifier: License :: OSI Approved :: GNU General Public License v3 or later (GPLv3+)
Classifier: Programming Language :: Python :: 3
Classifier: Programming Language :: Python :: 3.6
Classifier: Programming Language :: Python :: 3.7
Classifier: Programming Language :: Python :: 3.8
Requires-Dist: bs4 (>=0.0.1,<0.0.2)
Requires-Dist: getopt2 (>=0.0.3,<0.0.4)
Requires-Dist: lxml (>=4.5.0,<5.0.0)
Requires-Dist: requests (>=2.23.0,<3.0.0)
Project-URL: Repository, https://github.com/ccdale/manjaro-torrent-find
